setup.py
eosproxy/__init__.py
eosproxy/__version__.py
eosproxy/cleos.py
eosproxy/command_line.py
eosproxy/dynamic_url.py
eosproxy/exceptions.py
eosproxy/keys.py
eosproxy/schemaeospy.py
eosproxy/signer.py
eosproxy/testeos.py
eosproxy/typeseos.py
eosproxy/utils.py
eosproxy.egg-info/PKG-INFO
eosproxy.egg-info/SOURCES.txt
eosproxy.egg-info/dependency_links.txt
eosproxy.egg-info/not-zip-safe
eosproxy.egg-info/requires.txt
eosproxy.egg-info/top_level.txt